datasource/.version
datasource/__classpath__.py
datasource/__init__.py
datasource/crud_entity.py
datasource/crud_repository.py
datasource/crud_service.py
datasource/db_configuration.py
datasource/db_repository.py
datasource/identity.py
datasource/exception/__init__.py
datasource/exception/exceptions.py
datasource/firebase/__init__.py
datasource/firebase/firebase_configuration.py
datasource/firebase/firebase_repository.py
datasource/mysql/__init__.py
datasource/mysql/mysql_repository.py
datasource/redis/__init__.py
datasource/redis/redis_configuration.py
datasource/redis/redis_repository.py
datasource/sqlite/__init__.py
datasource/sqlite/sqlite_repository.py
hspylib_datasource-0.9.82.dist-info/METADATA
hspylib_datasource-0.9.82.dist-info/WHEEL
hspylib_datasource-0.9.82.dist-info/top_level.txt
hspylib_datasource-0.9.82.dist-info/RECORD
