Metadata-Version: 2.1
Name: hspylib-datasource
Version: 0.9.82
Summary: HsPyLib - Datasource integration
Home-page: https://github.com/yorevs/hspylib
Author: Hugo Saporetti Junior
Author-email: yorevs@hotmail.com
License: MIT
Project-URL: GitHub, https://github.com/yorevs/hspylib
Project-URL: PyPi, https://pypi.org/project/hspylib-datasource/
Keywords: datasource,database,sql,nosql,db
Platform: Darwin
Platform: Linux
Classifier: License :: OSI Approved :: MIT License
Classifier: Programming Language :: Python :: 3.10
Classifier: Operating System :: MacOS :: MacOS X
Classifier: Operating System :: POSIX :: Linux
Classifier: Operating System :: Unix
Classifier: Development Status :: 2 - Pre-Alpha
Classifier: Environment :: Console
Classifier: Natural Language :: English
Classifier: Topic :: Software Development :: Libraries :: Python Modules
Classifier: Topic :: Software Development :: Libraries :: Application Frameworks
Classifier: Intended Audience :: Developers
Requires-Python: >=3.10
Requires-Dist: hspylib
Requires-Dist: retry2 >=0.9.5
Requires-Dist: requests >=2.32.3
Requires-Dist: urllib3 >=1.26.20
Requires-Dist: PyMySQL >=1.1.1
Requires-Dist: redis >=5.0.7
